srptools/__init__.py
srptools/cli.py
srptools/client.py
srptools/common.py
srptools/constants.py
srptools/context.py
srptools/exceptions.py
srptools/server.py
srptools/utils.py
srptools-1.0.0.dist-info/DESCRIPTION.rst
srptools-1.0.0.dist-info/METADATA
srptools-1.0.0.dist-info/RECORD
srptools-1.0.0.dist-info/WHEEL
srptools-1.0.0.dist-info/entry_points.txt
srptools-1.0.0.dist-info/metadata.json
srptools-1.0.0.dist-info/top_level.txt
